riscv/src/testbench/rs/parameters.v
//我们约定 所有的数字均为0-base
`define InstrLength 5'b11111
`define DataLength 5'b11111
`define UnsignedCharLength 3'b111
`define Zero 1'b0
`define PcLength 5'b11111
`define True 1'b1
`define False 1'b0
`define RegFileLength 5'b11111
`define OpcodeLength 3'b101

`define LUI 6'b000000
`define AUIPC 6'b000001
`define JAL 6'b000010
`define JALR 6'b000011
`define BEQ 6'b000100
`define BNE 6'b000101
`define BLT 6'b000110
`define BGE 6'b000111
`define BLTU 6'b001000
`define BGEU 6'b001001
`define LB 6'b001010
`define LH 6'b001011
`define LW 6'b001100
`define LBU 6'b001101
`define LHU 6'b001110
`define SB 6'b001111
`define SH 6'b010000
`define SW 6'b010001
`define ADDI 6'b010010
`define SLTI 6'b010011
`define SLTIU 6'b010100
`define XORI 6'b010101
`define ORI 6'b010110
`define ANDI 6'b010111
`define SLLI 6'b011000
`define SRLI 6'b011001
`define SRAI 6'b011010
`define ADD 6'b011011
`define SUB 6'b011100
`define SLL 6'b011101
`define SLT 6'b011110
`define SLTU 6'b011111
`define XOR 6'b100000
`define SRL 6'b100001
`define SRA 6'b100010
`define OR 6'b100011
`define AND 6'b100100

riscv/src/testbench/rs/ReverseStation.v
`include "parameters.v"
module rs
#(
    parameter RsLength = 7
)
(
    input wire rst,
    input wire clk,
    input wire is_empty_from_rob,
    input wire is_sl_from_rob,
    input wire is_exception_from_rob,
    input wire is_commit_from_rob,
    input wire[`OpcodeLength:`Zero] op_from_rob,
    input wire[`DataLength:`Zero] v1_from_rob,
    input wire[`DataLength:`Zero] v2_from_rob,
    input wire[`PcLength:`Zero] q1_from_rob,
    input wire[`PcLength:`Zero] q2_from_rob,
    input wire[`DataLength:`Zero] imm_from_rob,
    input wire[`DataLength:`Zero] pc_from_rob,
    input wire[`DataLength:`Zero] commit_data_from_rob,
    input wire[`PcLength:`Zero] commit_pc_from_rob,
    output wire[`OpcodeLength:`Zero] op_to_alu,
    output wire[`DataLength:`Zero] v1_to_alu,
    output wire[`DataLength:`Zero] v2_to_alu,
    output wire[`DataLength:`Zero] imm_to_alu,
    output wire[`DataLength:`Zero] pc_to_alu,
    output wire is_stall_to_instr_queue,
    output wire is_stall_to_rob
);
reg [`DataLength:`Zero] Value1[RsLength:`Zero];
reg [`DataLength:`Zero] Value2[RsLength:`Zero];
reg [`PcLength:`Zero] Queue1[RsLength:`Zero];
reg [`PcLength:`Zero] Queue2[RsLength:`Zero];
reg [`OpcodeLength:`Zero] Op[RsLength:`Zero];
reg is_busy[RsLength:`Zero];
reg is_stall;
reg [`DataLength:`Zero] Imm[RsLength:`Zero];
reg [`PcLength:`Zero] Pc[RsLength:`Zero];
reg [`DataLength:`Zero] v1;
reg [`DataLength:`Zero] v2;
reg [`DataLength:`Zero] imm;
reg [`PcLength:`Zero] pc;
reg [`OpcodeLength:`Zero] op;
integer i;
always @(posedge rst) begin
    is_stall <= 0;
    v1 <= 0;
    v2 <= 0;
    imm <= 0;
    op <= 0;
    for(i = 0 ;i <= RsLength; ++i) begin
        Value1[i] <= 0;
        Value2[i] <= 0;
        Queue1[i] <= 0;
        Queue2[i] <= 0;
        is_busy[i] <= 0;
        Pc[i] <= 0;
        Imm[i] <= 0; 
    end
end
always @(posedge clk) begin
    //判断是否清空
    if(is_exception_from_rob) begin
        is_stall <= 0;
        v1 <= 0;
        v2 <= 0;
        imm <= 0;
        for(i = 0 ; i <= RsLength ; ++i) begin
            Value1[i] <= 0;
            Value2[i] <= 0;
            Queue1[i] <= 0;
            Queue2[i] <= 0;
            is_busy[i] <= 0;
            Pc[i] <= 0;
            Imm[i] <= 0; 
            Op[i] <= 0;
        end
    end
    else begin
        if(is_empty_from_rob == `False && is_sl_from_rob == `False) begin
            //先用rob的提交更新
            if(is_commit_from_rob) begin
                for(i = 0 ; i <= RsLength ; ++i) begin
                    if(is_busy[i] == `True && Queue1[i] == 0 && Queue2[i] == 0) begin
                        if(Queue1[i] == commit_pc_from_rob)begin
                            Queue1[i] = 0;
                            Value1[i] = commit_data_from_rob;
                        end
                        if(Queue2[i] == commit_pc_from_rob) begin
                            Queue2[i] = 0;
                            Value2[i] = commit_data_from_rob;
                        end
                    end
                end
            end
            //再找一遍可以发射的
            begin : loop
                for(i = 0 ; i <= RsLength ; ++i) begin
                    if(is_busy[i] == `True && Queue1[i] == 0 && Queue2[i] == 0) begin
                        v1 = Value1[i];
                        v2 = Value2[i];
                        imm = Imm[i];
                        pc = Pc[i];
                        op = Op[i];
                        is_busy[i] = `False;
                        disable loop;
                    end
                end
            end
            //再输入新的来自rob的值
            begin : loop2 
                is_stall = `True;
                for(i = 0 ; i <= RsLength ; ++i) begin
                    if(is_busy[i] == `False) begin
                        Pc[i] = pc_from_rob;
                        Imm[i] = imm_from_rob;
                        Value1[i] = v1_from_rob;
                        Value2[i] = v2_from_rob;
                        Queue1[i] = q1_from_rob;
                        Queue2[i] = q2_from_rob;
                        Op[i] = op_from_rob;
                        is_busy[i] = `True;
                        is_stall = `False;
                        disable loop2;
                    end
                end
            end
        end
    end
end
assign v1_to_alu = v1;
assign v2_to_alu = v2;
assign imm_to_alu = imm;
assign pc_to_alu = pc;
assign is_stall_to_instr_queue = is_stall;
assign is_stall_to_rob = is_stall;
assign op_to_alu = op;
endmodule

riscv/src/testbench/rs/trs.v
`include"parameters.v"
`include"ReverseStation.v"
`timescale  1ns / 1ps

module tb_rs;        

// rs Parameters
parameter PERIOD    = 10;
parameter RsLength  = 7;

// rs Inputs
reg   rst_n                                  = 0 ;
reg   clk                                  = 0 ;
reg   is_empty_from_rob                    = 0 ;
reg   is_sl_from_rob                       = 0 ;
reg   is_exception_from_rob                = 0 ;
reg   is_commit_from_rob                   = 0 ;
reg   [`OpcodeLength:`Zero] op_from_rob = 0 ;
reg   [`DataLength:`Zero] v1_from_rob  = 0 ;
reg   [`DataLength:`Zero] v2_from_rob  = 0 ;
reg   [`PcLength:`Zero] q1_from_rob    = 0 ;
reg   [`PcLength:`Zero] q2_from_rob    = 0 ;
reg   [`DataLength:`Zero] imm_from_rob = 0 ;
reg   [`DataLength:`Zero] pc_from_rob  = 0 ;
reg   [`DataLength:`Zero] commit_data_from_rob = 0 ;
reg   [`PcLength:`Zero] commit_pc_from_rob = 0 ;

// rs Outputs
wire  [`OpcodeLength:`Zero] op_to_alu  ;
wire  [`DataLength:`Zero] v1_to_alu    ;
wire  [`DataLength:`Zero] v2_to_alu    ;
wire  [`DataLength:`Zero] imm_to_alu   ;
wire  [`DataLength:`Zero] pc_to_alu    ;
wire  is_stall_to_instr_queue              ;
wire  is_stall_to_rob                      ;


initial
begin
    #(PERIOD*2) rst_n  =  1;
    forever #(PERIOD/2)  clk=~clk;
end


rs #(
    .RsLength ( RsLength ))
 u_rs (
    .rst                                           ( rst_n                                            ),
    .clk                                           ( clk                                            ),
    .is_empty_from_rob                             ( is_empty_from_rob                              ),
    .is_sl_from_rob                                ( is_sl_from_rob                                 ),
    .is_exception_from_rob                         ( is_exception_from_rob                          ),
    .is_commit_from_rob                            ( is_commit_from_rob                             ),
    .op_from_rob         ( op_from_rob          ),
    .v1_from_rob           (  v1_from_rob            ),
    .v2_from_rob           (  v2_from_rob            ),
    .q1_from_rob             (  q1_from_rob              ),
    .q2_from_rob             ( q2_from_rob              ),
    .imm_from_rob          ( imm_from_rob           ),
    .pc_from_rob           ( pc_from_rob            ),
    .commit_data_from_rob  ( commit_data_from_rob   ),
    .commit_pc_from_rob      ( commit_pc_from_rob       ),

    .op_to_alu           ( op_to_alu            ),
    .v1_to_alu             ( v1_to_alu              ),
    .v2_to_alu             ( v2_to_alu              ),
    .imm_to_alu            ( imm_to_alu             ),
    .pc_to_alu             ( pc_to_alu              ),
    .is_stall_to_instr_queue                       ( is_stall_to_instr_queue                        ),
    .is_stall_to_rob                               ( is_stall_to_rob                                )
);

initial
begin
    $dumpfile("test.vcd");
    $dumpvars(0,tb_rs);
    #100;
    $finish;
end

endmodule

riscv/src/testbench/rs/test.vcd
$date
	Tue Nov 16 19:33:10 2021
$end
$version
	Icarus Verilog
$end
$timescale
	1ps
$end
$scope module tb_rs $end
$var wire 32 ! v2_to_alu [31:0] $end
$var wire 32 " v1_to_alu [31:0] $end
$var wire 32 # pc_to_alu [31:0] $end
$var wire 6 $ op_to_alu [5:0] $end
$var wire 1 % is_stall_to_rob $end
$var wire 1 & is_stall_to_instr_queue $end
$var wire 32 ' imm_to_alu [31:0] $end
$var reg 1 ( clk $end
$var reg 32 ) commit_data_from_rob [31:0] $end
$var reg 32 * commit_pc_from_rob [31:0] $end
$var reg 32 + imm_from_rob [31:0] $end
$var reg 1 , is_commit_from_rob $end
$var reg 1 - is_empty_from_rob $end
$var reg 1 . is_exception_from_rob $end
$var reg 1 / is_sl_from_rob $end
$var reg 6 0 op_from_rob [5:0] $end
$var reg 32 1 pc_from_rob [31:0] $end
$var reg 32 2 q1_from_rob [31:0] $end
$var reg 32 3 q2_from_rob [31:0] $end
$var reg 1 4 rst_n $end
$var reg 32 5 v1_from_rob [31:0] $end
$var reg 32 6 v2_from_rob [31:0] $end
$scope module u_rs $end
$var wire 1 ( clk $end
$var wire 32 7 commit_data_from_rob [31:0] $end
$var wire 32 8 commit_pc_from_rob [31:0] $end
$var wire 32 9 imm_from_rob [31:0] $end
$var wire 32 : imm_to_alu [31:0] $end
$var wire 1 , is_commit_from_rob $end
$var wire 1 - is_empty_from_rob $end
$var wire 1 . is_exception_from_rob $end
$var wire 1 / is_sl_from_rob $end
$var wire 1 & is_stall_to_instr_queue $end
$var wire 1 % is_stall_to_rob $end
$var wire 6 ; op_from_rob [5:0] $end
$var wire 6 < op_to_alu [5:0] $end
$var wire 32 = pc_from_rob [31:0] $end
$var wire 32 > pc_to_alu [31:0] $end
$var wire 32 ? q1_from_rob [31:0] $end
$var wire 32 @ q2_from_rob [31:0] $end
$var wire 1 4 rst $end
$var wire 32 A v1_from_rob [31:0] $end
$var wire 32 B v1_to_alu [31:0] $end
$var wire 32 C v2_from_rob [31:0] $end
$var wire 32 D v2_to_alu [31:0] $end
$var reg 32 E imm [31:0] $end
$var reg 1 F is_stall $end
$var reg 6 G op [5:0] $end
$var reg 32 H pc [31:0] $end
$var reg 32 I v1 [31:0] $end
$var reg 32 J v2 [31:0] $end
$var integer 32 K i [31:0] $end
$scope begin loop $end
$upscope $end
$scope begin loop2 $end
$upscope $end
$upscope $end
$upscope $end
$enddefinitions $end
#0
$dumpvars
bx K
bx J
bx I
bx H
bx G
xF
bx E
bx D
b0 C
bx B
b0 A
b0 @
b0 ?
bx >
b0 =
bx <
b0 ;
bx :
b0 9
b0 8
b0 7
b0 6
b0 5
04
b0 3
b0 2
b0 1
b0 0
0/
0.
0-
0,
b0 +
b0 *
b0 )
0(
bx '
x&
x%
bx $
bx #
bx "
bx !
$end
#20000
b0 $
b0 <
b0 G
b0 '
b0 :
b0 E
b0 !
b0 D
b0 J
b0 "
b0 B
b0 I
0%
0&
0F
b1000 K
14
#25000
0%
0&
0F
b0 K
1(
#30000
0(
#35000
b1 K
0%
0&
0F
b0 #
b0 >
b0 H
1(
#40000
0(
#45000
0%
0&
0F
b10 K
1(
#50000
0(
#55000
0%
0&
0F
b11 K
1(
#60000
0(
#65000
0%
0&
0F
b100 K
1(
#70000
0(
#75000
0%
0&
0F
b101 K
1(
#80000
0(
#85000
0%
0&
0F
b110 K
1(
#90000
0(
#95000
0%
0&
0F
b111 K
1(
